amazon_paapi/__init__.py
amazon_paapi/api.py
amazon_paapi/errors/__init__.py
amazon_paapi/errors/exceptions.py
amazon_paapi/helpers/__init__.py
amazon_paapi/helpers/arguments.py
amazon_paapi/helpers/generators.py
amazon_paapi/helpers/items.py
amazon_paapi/helpers/requests.py
amazon_paapi/models/__init__.py
amazon_paapi/models/browse_nodes_result.py
amazon_paapi/models/item_result.py
amazon_paapi/models/regions.py
amazon_paapi/models/search_result.py
amazon_paapi/models/variations_result.py
amazon_paapi/sdk/__init__.py
amazon_paapi/sdk/api_client.py
amazon_paapi/sdk/configuration.py
amazon_paapi/sdk/rest.py
amazon_paapi/sdk/api/__init__.py
amazon_paapi/sdk/api/default_api.py
amazon_paapi/sdk/auth/__init__.py
amazon_paapi/sdk/auth/sign_helper.py
amazon_paapi/sdk/models/__init__.py
amazon_paapi/sdk/models/availability.py
amazon_paapi/sdk/models/browse_node.py
amazon_paapi/sdk/models/browse_node_ancestor.py
amazon_paapi/sdk/models/browse_node_child.py
amazon_paapi/sdk/models/browse_node_info.py
amazon_paapi/sdk/models/browse_nodes_result.py
amazon_paapi/sdk/models/by_line_info.py
amazon_paapi/sdk/models/classifications.py
amazon_paapi/sdk/models/condition.py
amazon_paapi/sdk/models/content_info.py
amazon_paapi/sdk/models/content_rating.py
amazon_paapi/sdk/models/contributor.py
amazon_paapi/sdk/models/customer_reviews.py
amazon_paapi/sdk/models/delivery_flag.py
amazon_paapi/sdk/models/dimension_based_attribute.py
amazon_paapi/sdk/models/duration_price.py
amazon_paapi/sdk/models/error_data.py
amazon_paapi/sdk/models/external_ids.py
amazon_paapi/sdk/models/get_browse_nodes_request.py
amazon_paapi/sdk/models/get_browse_nodes_resource.py
amazon_paapi/sdk/models/get_browse_nodes_response.py
amazon_paapi/sdk/models/get_items_request.py
amazon_paapi/sdk/models/get_items_resource.py
amazon_paapi/sdk/models/get_items_response.py
amazon_paapi/sdk/models/get_variations_request.py
amazon_paapi/sdk/models/get_variations_resource.py
amazon_paapi/sdk/models/get_variations_response.py
python_amazon_paapi-5.0.0.dist-info/LICENSE
python_amazon_paapi-5.0.0.dist-info/METADATA
python_amazon_paapi-5.0.0.dist-info/WHEEL
python_amazon_paapi-5.0.0.dist-info/top_level.txt
python_amazon_paapi-5.0.0.dist-info/RECORD
