Metadata-Version: 2.1
Name: python-amazon-paapi
Version: 5.0.0
Summary: Amazon Product Advertising API 5.0 wrapper for Python
Home-page: https://github.com/sergioteula/python-amazon-paapi
Author: Sergio Abad
Author-email: sergio.abad@bytelix.com
License: MIT
Classifier: Programming Language :: Python
Classifier: License :: OSI Approved :: MIT License
Classifier: Operating System :: OS Independent
Requires-Python: >=3.6
License-File: LICENSE
